{
    "overview.inventory.champion.akshan.price_rp": "<span>975</span>",
    "overview.inventory.champion.akshan.price_be.featured": "<span>7800</span>",
    "overview.inventory.skin.sentinel_vayne.price": "<span>1820</span>",
    "overview.inventory.skin.sentinel_olaf.price": "<span>1350</span>",
    "overview.inventory.skin.sentinel_riven.price": "<span>1350</span>",
    "overview.inventory.skin.sentinel_irelia.price": "<span>1350</span>",
    "overview.inventory.skin.sentinel_diana.price": "<span>1350</span>",
    "overview.inventory.skin.ruined_pantheon.price": "<span>1350</span>",
    "overview.inventory.skin.sentinel_graves.price": "<span>1820</span>",
    "overview.inventory.skin.sentinel_pyke.price": "<span>1350</span>",
    "overview.inventory.skin.ruined_miss_fortune.price": "<span>1350</span>",
    "overview.inventory.skin.sentinel_rengar.price": "<span>1350</span>",
    "journal.shadow_isles.date": "val dne",
    "journal.shadow_isles.copy": "val dne",
    "journal.shurima.date": "val dne",
    "journal.shurima.copy": "val dne",
    "journal.shurima.unlock_note": "val dne",
    "journal.shurima.upgrade_name": "val dne",
    "journal.shurima.upgrade_description": "val dne",
    "journal.key_upgrade.b1.date": "val dne",
    "journal.key_upgrade.b1.copy": "val dne",
    "journal.key_upgrade.b1.unlock_note": "val dne",
    "journal.key_upgrade.b1.upgrade_name": "val dne",
    "journal.key_upgrade.b1.upgrade_description": "val dne",
    "journal.key_upgrade.b2.date": "val dne",
    "journal.key_upgrade.b2.copy": "val dne",
    "journal.key_upgrade.b2.unlock_note": "val dne",
    "journal.key_upgrade.b2.upgrade_name": "val dne",
    "journal.key_upgrade.b2.upgrade_description": "val dne",
    "journal.key_upgrade.b3.date": "val dne",
    "journal.key_upgrade.b3.copy": "val dne",
    "journal.key_upgrade.b3.unlock_note": "val dne",
    "journal.key_upgrade.b3.upgrade_name": "val dne",
    "journal.key_upgrade.b3.upgrade_description": "val dne",
    "journal.key_upgrade.b4.date": "val dne",
    "journal.key_upgrade.b4.copy": "val dne",
    "journal.key_upgrade.b4.unlock_note": "val dne",
    "journal.key_upgrade.b4.upgrade_name": "val dne",
    "journal.key_upgrade.b4.upgrade_description": "val dne",
    "journal.key_upgrade.b5.date": "val dne",
    "journal.key_upgrade.b5.copy": "val dne",
    "journal.key_upgrade.b5.unlock_note": "val dne",
    "journal.key_upgrade.b5.upgrade_name": "val dne",
    "journal.key_upgrade.b5.upgrade_description": "val dne",
    "journal.key_upgrade.b6.date": "val dne",
    "journal.key_upgrade.b6.copy": "val dne",
    "journal.key_upgrade.b6.unlock_note": "val dne",
    "journal.key_upgrade.b6.upgrade_name": "val dne",
    "journal.key_upgrade.b6.upgrade_description": "val dne",
    "journal.key_upgrade.b7.date": "val dne",
    "journal.key_upgrade.b7.copy": "val dne",
    "journal.key_upgrade.b7.unlock_note": "val dne",
    "journal.key_upgrade.b7.upgrade_name": "val dne",
    "journal.key_upgrade.b7.upgrade_description": "val dne",
    "journal.key_upgrade.b8.date": "val dne",
    "journal.key_upgrade.b8.copy": "val dne",
    "journal.key_upgrade.b8.unlock_note": "val dne",
    "journal.key_upgrade.b8.upgrade_name": "val dne",
    "journal.key_upgrade.b8.upgrade_description": "val dne",
    "journal.week_4.date": "val dne",
    "journal.week_4.copy": "val dne",
    "journal.week_4.unlock_note": "val dne",
    "journal.week_4.upgrade_name": "val dne",
    "journal.week_4.upgrade_description": "val dne",
    "journal.bilgewater_b.date": "val dne",
    "journal.bilgewater_b.copy": "val dne",
    "journal.bilgewater_b.unlock_note": "val dne",
    "journal.bilgewater_b.upgrade_name": "val dne",
    "journal.bilgewater_b.upgrade_description": "val dne",
    "journal.ixtal_b.date": "val dne",
    "journal.ixtal_b.copy": "val dne",
    "journal.ixtal_b.unlock_note": "val dne",
    "journal.ixtal_b.upgrade_name": "val dne",
    "journal.ixtal_b.upgrade_description": "val dne",
    "journal.bilgewater_a.date": "val dne",
    "journal.bilgewater_a.copy": "val dne",
    "journal.bilgewater_a.unlock_note": "val dne",
    "journal.bilgewater_a.upgrade_name": "val dne",
    "journal.bilgewater_a.upgrade_description": "val dne",
    "journal.ixtal_a.date": "val dne",
    "journal.ixtal_a.copy": "val dne",
    "journal.ixtal_a.unlock_note": "val dne",
    "journal.ixtal_a.upgrade_name": "val dne",
    "journal.ixtal_a.upgrade_description": "val dne",
    "journal.piltover_zaun.date": "val dne",
    "journal.piltover_zaun.copy": "val dne",
    "journal.piltover_zaun.unlock_note": "val dne",
    "journal.piltover_zaun.upgrade_name": "val dne",
    "journal.piltover_zaun.upgrade_description": "val dne",
    "journal.key_upgrade.a1.date": "val dne",
    "journal.key_upgrade.a1.copy": "val dne",
    "journal.key_upgrade.a1.unlock_note": "val dne",
    "journal.key_upgrade.a1.upgrade_name": "val dne",
    "journal.key_upgrade.a1.upgrade_description": "val dne",
    "journal.key_upgrade.a2.date": "val dne",
    "journal.key_upgrade.a2.copy": "val dne",
    "journal.key_upgrade.a2.unlock_note": "val dne",
    "journal.key_upgrade.a2.upgrade_name": "val dne",
    "journal.key_upgrade.a2.upgrade_description": "val dne",
    "journal.key_upgrade.a3.date": "val dne",
    "journal.key_upgrade.a3.copy": "val dne",
    "journal.key_upgrade.a3.unlock_note": "val dne",
    "journal.key_upgrade.a3.upgrade_name": "val dne",
    "journal.key_upgrade.a3.upgrade_description": "val dne",
    "journal.key_upgrade.a4.date": "val dne",
    "journal.key_upgrade.a4.copy": "val dne",
    "journal.key_upgrade.a4.unlock_note": "val dne",
    "journal.key_upgrade.a4.upgrade_name": "val dne",
    "journal.key_upgrade.a4.upgrade_description": "val dne",
    "journal.week_3.date": "val dne",
    "journal.week_3.copy": "val dne",
    "journal.week_3.unlock_note": "val dne",
    "journal.week_3.upgrade_name": "val dne",
    "journal.week_3.upgrade_description": "val dne",
    "journal.targon_b.date": "DAY 115",
    "journal.targon_b.copy": "Something tells me Irelia didn't expect another holy pilgrimage right after the last one. She probably could have done without the whole \"confronting the Aspect of War\" thing. I know I could have!",
    "journal.targon_b.unlock_note": "RECRUITED",
    "journal.targon_b.upgrade_name": "Serene",
    "journal.targon_b.upgrade_description": "Diana",
    "journal.ionia_b.date": "DAY 115",
    "journal.ionia_b.copy": "I wonder if Diana ever expected to be this far from Mount Targon? I certainly didn't expect to be this far from headquarters... but Ionia needs me. Well, the sentinels. It sounds like Senna has a better idea of what we're facing now.",
    "journal.ionia_b.unlock_note": "RECRUITED",
    "journal.ionia_b.upgrade_name": "Swift",
    "journal.ionia_b.upgrade_description": "Irelia",
    "journal.targon_a.date": "DAY 112",
    "journal.targon_a.copy": "Starting to think they only keep me around for my Wayfinder. If Lucian wanted to trade it for one of his guns, I wouldn't complain. Would've been nice to have one of those when staring down the Aspect of War.",
    "journal.targon_a.unlock_note": "RECRUITED",
    "journal.targon_a.upgrade_name": "Vengeful",
    "journal.targon_a.upgrade_description": "Diana",
    "journal.ionia_a.date": "DAY 112",
    "journal.ionia_a.copy": "Wish I'd had a gun or something when facing down the all-powerful Spirit of Ionia. Anything besides this Wayfinder. Still, we understand a little more about how to stop this now. Well, Senna does. I just go where they tell me.",
    "journal.ionia_a.unlock_note": "RECRUITED",
    "journal.ionia_a.upgrade_name": "Patient",
    "journal.ionia_a.upgrade_description": "Irelia",
    "journal.week_2.date": "DAY 111",
    "journal.week_2.copy": "Next stop, Ionia and Targon. When Senna and Lucian showed up, I didn't expect this...",
    "journal.week_2.unlock_note": "UNLOCKED",
    "journal.week_2.upgrade_name": "Chapter II",
    "journal.week_2.upgrade_description": "Click to view",
    "journal.noxus_b.date": "DAY 107",
    "journal.noxus_b.copy": "\"I hope the next sentinel's somewhere warmer than the Freljord,\" I said. Note to self: specify no arena combat for next time. And no fetter! Nice of Riven to help us out, though.",
    "journal.noxus_b.unlock_note": "RECRUITED",
    "journal.noxus_b.upgrade_name": "Reforged",
    "journal.noxus_b.upgrade_description": "Riven",
    "journal.freljord_b.date": "DAY 107",
    "journal.freljord_b.copy": "We made it through the Freljord! Hope the next place we go is warmer. We got a new sentinel, too. Riven doesn't seem impressed by his smell.",
    "journal.freljord_b.unlock_note": "RECRUITED",
    "journal.freljord_b.upgrade_name": "Berserk",
    "journal.freljord_b.upgrade_description": "Olaf",
    "journal.noxus_a.date": "DAY 105",
    "journal.noxus_a.copy": "Draven finally answers the question: What's worse than an egomaniac? An egomaniac surrounded by wraiths. Glad we met Riven, though. She sure was handy during the gladiator fight. Well, the second one.",
    "journal.noxus_a.unlock_note": "RECRUITED",
    "journal.noxus_a.upgrade_name": "Defiant",
    "journal.noxus_a.upgrade_description": "Riven",
    "journal.freljord_a.date": "DAY 105",
    "journal.freljord_a.copy": "Ran across a very strange man in the Freljord. Not sure what he smells like, but it's not great. And he's going to be a sentinel? I hope the next one we recruit's from somewhere warmer...",
    "journal.freljord_a.unlock_note": "RECRUITED",
    "journal.freljord_a.upgrade_name": "Enraged",
    "journal.freljord_a.upgrade_description": "Olaf",
    "journal.demacia.date": "DAY 101",
    "journal.demacia.copy": "Demacia is safe now. Or as safe as any place can be while a Harrowing's still happening. We cleared out a bunch of wraiths. I met a dragon. And Vayne. Not sure which one's scarier.",
    "journal.demacia.unlock_note": "RECRUITED",
    "journal.demacia.upgrade_name": "val dne",
    "journal.demacia.upgrade_description": "Vayne",
    "journal.event_begin.date": "DAY 98",
    "journal.week_1.date": "DAY 97",
    "journal.week_1.copy": "Wraiths and a worldwide harrowing. Life just got interesting.",
    "journal.week_1.unlock_note": "UNLOCKED",
    "journal.week_1.upgrade_name": "Chapter I",
    "journal.week_1.upgrade_description": "Click to view",
    "journal.event_begin.copy": "After all this time... people! Two new sentinels. Lucian and Senna seemed preoccupied by this \"Harrowing\" they talked about. That doesn't sound good...",
    "profile.diana_b.clause_1": "10k+",
    "profile.diana_b.clause_2": "15k+",
    "profile.diana_b.clause_3": "20k+",
    "profile.diana_b.clause_4": "30k+",
    "profile.irelia_a.clause_1": "<15m",
    "profile.irelia_a.clause_2": "<22m",
    "profile.irelia_a.clause_3": "<28m",
    "profile.irelia_a.clause_4": "<35m",
    "profile.olaf_b.clause_1": "10k+",
    "profile.olaf_b.clause_2": "15k+",
    "profile.olaf_b.clause_3": "25k+",
    "profile.olaf_b.clause_4": "35k+",
    "profile.pyke_a.clause_1": "val dne",
    "profile.pyke_a.clause_2": "val dne",
    "profile.pyke_a.clause_3": "val dne",
    "profile.pyke_a.clause_4": "val dne",
    "profile.riven_a.clause_1": "3k+",
    "profile.riven_a.clause_2": "7k+",
    "profile.riven_a.clause_3": "12k+",
    "global_ui.info_settings_cta": "INFO & SETTINGS",
    "global_ui.tooltip.audio_on": "AUDIO ON",
    "global_ui.tooltip.motion_on": "ANIMATION ON"
}